sformat/__init__.py
sformat/formatter.py
sformat/main.py
sformat-0.1.0.dist-info/LICENSE
sformat-0.1.0.dist-info/METADATA
sformat-0.1.0.dist-info/WHEEL
sformat-0.1.0.dist-info/entry_points.txt
sformat-0.1.0.dist-info/top_level.txt
sformat-0.1.0.dist-info/RECORD
