Metadata-Version: 2.1
Name: sformat
Version: 0.1.0
Summary: Format an input stream using the section character
Home-page: https://github.com/
Author: Pursuit
Author-email: fr.pursuit@gmail.com
License: GNU General Public License v3 (GPLv3)
Platform: UNKNOWN
Classifier: Programming Language :: Python :: 3
Classifier: License :: OSI Approved :: GNU General Public License v3 (GPLv3)
Classifier: Operating System :: OS Independent
Requires-Python: >=3.7
License-File: LICENSE
